stubs/pyang/__init__.pyi
stubs/pyang/context.pyi
stubs/pyang/error.pyi
stubs/pyang/plugin.pyi
stubs/pyang/statements.pyi
stubs/pyang/xpath.pyi
yang_scan/__init__.py
yang_scan/scan.py
yang_scan-1.1.0.data/data/etc/yang-scan/README.rst
yang_scan-1.1.0.dist-info/AUTHORS
yang_scan-1.1.0.dist-info/LICENSE
yang_scan-1.1.0.dist-info/METADATA
yang_scan-1.1.0.dist-info/WHEEL
yang_scan-1.1.0.dist-info/entry_points.txt
yang_scan-1.1.0.dist-info/pbr.json
yang_scan-1.1.0.dist-info/top_level.txt
yang_scan-1.1.0.dist-info/RECORD
