Metadata-Version: 2.1
Name: yang-scan
Version: 1.1.0
Summary: Pyang plugin scanning YANG modules
Home-page: https://gitlab.com/nso-developer/yang-scan
Author: UNKNOWN
Author-email: UNKNOWN
License: Apache-2.0
Keywords: YANG
Platform: UNKNOWN
Classifier: Development Status :: 4 - Beta
Classifier: Intended Audience :: Developers
Classifier: Intended Audience :: System Administrators
Classifier: Intended Audience :: Telecommunications Industry
Classifier: Topic :: System :: Networking
Classifier: Topic :: System :: Networking :: Monitoring
Classifier: License :: OSI Approved :: Apache Software License
Classifier: Programming Language :: Python :: 3.8
Classifier: Programming Language :: Python :: 3.9
Classifier: Programming Language :: Python :: 3.10
Requires-Dist: pyang
